tkintertools/mpl/__init__.py
tkintertools/mpl/constants.py
tkintertools/mpl/main.py
tkintertools_mpl-1.2.3.dist-info/LICENSE.txt
tkintertools_mpl-1.2.3.dist-info/METADATA
tkintertools_mpl-1.2.3.dist-info/WHEEL
tkintertools_mpl-1.2.3.dist-info/top_level.txt
tkintertools_mpl-1.2.3.dist-info/RECORD
