Metadata-Version: 2.2
Name: tkintertools-mpl
Version: 1.2.3
Summary: Extension package for tkintertools to matplotlib
Author-email: Xiaokang2022 <2951256653@qq.com>
Maintainer-email: Xiaokang2022 <2951256653@qq.com>
License: MIT License
Project-URL: Bug tracker, https://github.com/Xiaokang2022/tkintertools-mpl/issues
Project-URL: Source code, https://github.com/Xiaokang2022/tkintertools-mpl
Keywords: tkinter,tkintertools,matplotlib,cross-platform,themed
Classifier: Programming Language :: Python :: 3
Classifier: License :: OSI Approved :: MIT License
Classifier: Operating System :: Microsoft :: Windows
Classifier: Operating System :: POSIX :: Linux
Classifier: Operating System :: MacOS
Classifier: Intended Audience :: Developers
Classifier: Typing :: Typed
Requires-Python: >=3.10
License-File: LICENSE.txt
Requires-Dist: typing-extensions
Requires-Dist: tkintertools>=3.0.0rc6
Requires-Dist: matplotlib>=3.7.0
